MANIFEST.in
README.rst
setup.cfg
setup.py
src/colab_gitlab/__init__.py
src/colab_gitlab/apps.py
src/colab_gitlab/data_importer.py
src/colab_gitlab/diazo.xml
src/colab_gitlab/filters.py
src/colab_gitlab/models.py
src/colab_gitlab/password_validators.py
src/colab_gitlab/search_indexes.py
src/colab_gitlab/signals.py
src/colab_gitlab/tasks.py
src/colab_gitlab/urls.py
src/colab_gitlab/views.py
src/colab_gitlab.egg-info/PKG-INFO
src/colab_gitlab.egg-info/SOURCES.txt
src/colab_gitlab.egg-info/dependency_links.txt
src/colab_gitlab.egg-info/not-zip-safe
src/colab_gitlab.egg-info/requires.txt
src/colab_gitlab.egg-info/top_level.txt
src/colab_gitlab/fixtures/__init__.py
src/colab_gitlab/locale/en/LC_MESSAGES/django.mo
src/colab_gitlab/locale/en/LC_MESSAGES/django.po
src/colab_gitlab/locale/es/LC_MESSAGES/django.mo
src/colab_gitlab/locale/es/LC_MESSAGES/django.po
src/colab_gitlab/locale/pt_BR/LC_MESSAGES/django.mo
src/colab_gitlab/locale/pt_BR/LC_MESSAGES/django.po
src/colab_gitlab/migrations/0001_initial.py
src/colab_gitlab/migrations/0002_auto_20151210_1653.py
src/colab_gitlab/migrations/__init__.py
src/colab_gitlab/templates/dashboard/comment_search_preview.html
src/colab_gitlab/templates/dashboard/issue_search_preview.html
src/colab_gitlab/templates/dashboard/merge_request_search_preview.html
src/colab_gitlab/templates/proxy/gitlab.html
src/colab_gitlab/templates/search/comment_search_preview.html
src/colab_gitlab/templates/search/issue_search_preview.html
src/colab_gitlab/templates/search/merge_request_search_preview.html
src/colab_gitlab/templates/search/project_search_preview.html
src/colab_gitlab/templates/search/indexes/colab_gitlab/gitlabcomment_text.txt
src/colab_gitlab/templates/search/indexes/colab_gitlab/gitlabissue_text.txt
src/colab_gitlab/templates/search/indexes/colab_gitlab/gitlabmergerequest_text.txt
src/colab_gitlab/templates/search/indexes/colab_gitlab/gitlabproject_text.txt
src/colab_gitlab/templates/widgets/gitlab_profile.html
src/colab_gitlab/templatetags/__init__.py
src/colab_gitlab/templatetags/gitlab_urls.py
src/colab_gitlab/widgets/__init__.py
src/colab_gitlab/widgets/profile/__init__.py
src/colab_gitlab/widgets/profile/diazo.xml
src/colab_gitlab/widgets/profile/profile.py