Metadata-Version: 1.1
Name: colab-gitlab
Version: 0.2.6
Summary: A Gitlab plugin for Colab
Home-page: https://github.com/colab/colab-gitlab-plugin
Author: Sergio Oliveira
Author-email: sergio@tracy.com.br
License: GPLv3
Platform: UNKNOWN
Classifier: Framework :: Django
Classifier: Intended Audience :: Developers
Classifier: Intended Audience :: System Administrators
Classifier: Operating System :: OS Independent
Classifier: Topic :: Software Development
